packaging_tutorial_simpleappdesigner/__about__.py
packaging_tutorial_simpleappdesigner/__init__.py
packaging_tutorial_simpleappdesigner/example.py
packaging_tutorial_simpleappdesigner-0.0.3.dist-info/METADATA
packaging_tutorial_simpleappdesigner-0.0.3.dist-info/WHEEL
packaging_tutorial_simpleappdesigner-0.0.3.dist-info/licenses/LICENSE.txt
packaging_tutorial_simpleappdesigner-0.0.3.dist-info/RECORD
